{
  "job_type": "render",
  "timestamp": "2025-08-11T19:19:08.240193",
  "metadata": {
    "video_name": "2025-05-02_19-39-31_UTC",
    "total_frames": 500,
    "frames_per_chunk": 101
  },
  "total_jobs": 10,
  "jobs": [
    {
      "job_id": "a993bf12-3fe5-4f55-855b-0343d1a467c0",
      "job_number": 1,
      "job_type": "HIGH",
      "frames_to_render": 101,
      "start_frame": 0,
      "video_name": "2025-05-02_19-39-31_UTC",
      "positive_prompt": "The setting to be an indoor space of a bedroom. OFA1M1 is wearing black short panties and a white crop bra\\nOFA1M1 is dancing to an upbeat, rhythmic song. Her movements are fluid and confident\\n\\n Her expressions vary from a seductive gaze at the camera to a playful smile. The video is well-lit and appears to be professionally shot, with a clear focus on the woman's dance and attire. \\n\\nsh4rpn3ss 4k HDR. clear skin, masterpiece, subscatering photorealistic skin texture, detailed skin, visible pores, subsurface scattering, fine vellus hair, subtle skin imperfections, natural freckles, subsurface scattering,soft natural volumetric cinematic light, 8k RAW photo, sharp focus, f/1.8 aperture, and shallow depth of field",
      "negative_prompt": "\u8272\u8c03\u8273\u4e3d\uff0c\u8fc7\u66dd\uff0c\u9759\u6001\uff0c\u7ec6\u8282\u6a21\u7cca\u4e0d\u6e05\uff0c\u5b57\u5e55\uff0c\u98ce\u683c\uff0c\u4f5c\u54c1\uff0c\u753b\u4f5c\uff0c\u753b\u9762\uff0c\u9759\u6b62\uff0c\u6574\u4f53\u53d1\u7070\uff0c\u6700\u5dee\u8d28\u91cf\uff0c\u4f4e\u8d28\u91cf\uff0cJPEG\u538b\u7f29\u6b8b\u7559\uff0c\u4e11\u964b\u7684\uff0c\u6b8b\u7f3a\u7684\uff0c\u591a\u4f59\u7684\u624b\u6307\uff0c\u753b\u5f97\u4e0d\u597d\u7684\u624b\u90e8\uff0c\u753b\u5f97\u4e0d\u597d\u7684\u8138\u90e8\uff0c\u7578\u5f62\u7684\uff0c\u6bc1\u5bb9\u7684\uff0c\u5f62\u6001\u7578\u5f62\u7684\u80a2\u4f53\uff0c\u624b\u6307\u878d\u5408\uff0c\u9759\u6b62\u4e0d\u52a8\u7684\u753b\u9762\uff0c\u6742\u4e71\u7684\u80cc\u666f\uff0c\u4e09\u6761\u817f\uff0c\u80cc\u666f\u4eba\u5f88\u591a\uff0c\u5012\u7740\u8d70, plastic skin, doll-like, airbrushed, perfectly smooth skin, cartoon, anime, 3d render, CGI, porcelain skin, oversaturated, unnatural color, jpeg artifacts, blurry, low quality, deformed, mutated",
      "latent_path": "output/prompt-runner/20250811_191908/latents/job_001.latent",
      "reference_image_path": "output/prompt-runner/20250811_191908/references/job_000_ref.png"
    },
    {
      "job_id": "540a6e01-244a-4783-9ce3-8e58060a4281",
      "job_number": 2,
      "job_type": "LOW",
      "frames_to_render": 101,
      "start_frame": 0,
      "video_name": "2025-05-02_19-39-31_UTC",
      "positive_prompt": "The setting to be an indoor space of a bedroom. OFA1M1 is wearing black short panties and a white crop bra\\nOFA1M1 is dancing to an upbeat, rhythmic song. Her movements are fluid and confident\\n\\n Her expressions vary from a seductive gaze at the camera to a playful smile. The video is well-lit and appears to be professionally shot, with a clear focus on the woman's dance and attire. \\n\\nsh4rpn3ss 4k HDR. clear skin, masterpiece, subscatering photorealistic skin texture, detailed skin, visible pores, subsurface scattering, fine vellus hair, subtle skin imperfections, natural freckles, subsurface scattering,soft natural volumetric cinematic light, 8k RAW photo, sharp focus, f/1.8 aperture, and shallow depth of field",
      "negative_prompt": "\u8272\u8c03\u8273\u4e3d\uff0c\u8fc7\u66dd\uff0c\u9759\u6001\uff0c\u7ec6\u8282\u6a21\u7cca\u4e0d\u6e05\uff0c\u5b57\u5e55\uff0c\u98ce\u683c\uff0c\u4f5c\u54c1\uff0c\u753b\u4f5c\uff0c\u753b\u9762\uff0c\u9759\u6b62\uff0c\u6574\u4f53\u53d1\u7070\uff0c\u6700\u5dee\u8d28\u91cf\uff0c\u4f4e\u8d28\u91cf\uff0cJPEG\u538b\u7f29\u6b8b\u7559\uff0c\u4e11\u964b\u7684\uff0c\u6b8b\u7f3a\u7684\uff0c\u591a\u4f59\u7684\u624b\u6307\uff0c\u753b\u5f97\u4e0d\u597d\u7684\u624b\u90e8\uff0c\u753b\u5f97\u4e0d\u597d\u7684\u8138\u90e8\uff0c\u7578\u5f62\u7684\uff0c\u6bc1\u5bb9\u7684\uff0c\u5f62\u6001\u7578\u5f62\u7684\u80a2\u4f53\uff0c\u624b\u6307\u878d\u5408\uff0c\u9759\u6b62\u4e0d\u52a8\u7684\u753b\u9762\uff0c\u6742\u4e71\u7684\u80cc\u666f\uff0c\u4e09\u6761\u817f\uff0c\u80cc\u666f\u4eba\u5f88\u591a\uff0c\u5012\u7740\u8d70, plastic skin, doll-like, airbrushed, perfectly smooth skin, cartoon, anime, 3d render, CGI, porcelain skin, oversaturated, unnatural color, jpeg artifacts, blurry, low quality, deformed, mutated",
      "latent_path": "output/prompt-runner/20250811_191908/latents/job_001.latent",
      "reference_image_path": "output/prompt-runner/20250811_191908/references/job_000_ref.png"
    },
    {
      "job_id": "343da9f7-e6e0-4e8f-bef6-3887f7aa88a3",
      "job_number": 3,
      "job_type": "HIGH",
      "frames_to_render": 101,
      "start_frame": 101,
      "video_name": "2025-05-02_19-39-31_UTC",
      "positive_prompt": "The setting to be an indoor space of a bedroom. OFA1M1 is wearing black short panties and a white crop bra\\nOFA1M1 is dancing to an upbeat, rhythmic song. Her movements are fluid and confident\\n\\n Her expressions vary from a seductive gaze at the camera to a playful smile. The video is well-lit and appears to be professionally shot, with a clear focus on the woman's dance and attire. \\n\\nsh4rpn3ss 4k HDR. clear skin, masterpiece, subscatering photorealistic skin texture, detailed skin, visible pores, subsurface scattering, fine vellus hair, subtle skin imperfections, natural freckles, subsurface scattering,soft natural volumetric cinematic light, 8k RAW photo, sharp focus, f/1.8 aperture, and shallow depth of field",
      "negative_prompt": "\u8272\u8c03\u8273\u4e3d\uff0c\u8fc7\u66dd\uff0c\u9759\u6001\uff0c\u7ec6\u8282\u6a21\u7cca\u4e0d\u6e05\uff0c\u5b57\u5e55\uff0c\u98ce\u683c\uff0c\u4f5c\u54c1\uff0c\u753b\u4f5c\uff0c\u753b\u9762\uff0c\u9759\u6b62\uff0c\u6574\u4f53\u53d1\u7070\uff0c\u6700\u5dee\u8d28\u91cf\uff0c\u4f4e\u8d28\u91cf\uff0cJPEG\u538b\u7f29\u6b8b\u7559\uff0c\u4e11\u964b\u7684\uff0c\u6b8b\u7f3a\u7684\uff0c\u591a\u4f59\u7684\u624b\u6307\uff0c\u753b\u5f97\u4e0d\u597d\u7684\u624b\u90e8\uff0c\u753b\u5f97\u4e0d\u597d\u7684\u8138\u90e8\uff0c\u7578\u5f62\u7684\uff0c\u6bc1\u5bb9\u7684\uff0c\u5f62\u6001\u7578\u5f62\u7684\u80a2\u4f53\uff0c\u624b\u6307\u878d\u5408\uff0c\u9759\u6b62\u4e0d\u52a8\u7684\u753b\u9762\uff0c\u6742\u4e71\u7684\u80cc\u666f\uff0c\u4e09\u6761\u817f\uff0c\u80cc\u666f\u4eba\u5f88\u591a\uff0c\u5012\u7740\u8d70, plastic skin, doll-like, airbrushed, perfectly smooth skin, cartoon, anime, 3d render, CGI, porcelain skin, oversaturated, unnatural color, jpeg artifacts, blurry, low quality, deformed, mutated",
      "latent_path": "output/prompt-runner/20250811_191908/latents/job_003.latent",
      "reference_image_path": "output/prompt-runner/20250811_191908/references/job_002_ref.png"
    },
    {
      "job_id": "acba7a56-be3d-4c99-be40-b6045a6a7d3c",
      "job_number": 4,
      "job_type": "LOW",
      "frames_to_render": 101,
      "start_frame": 101,
      "video_name": "2025-05-02_19-39-31_UTC",
      "positive_prompt": "The setting to be an indoor space of a bedroom. OFA1M1 is wearing black short panties and a white crop bra\\nOFA1M1 is dancing to an upbeat, rhythmic song. Her movements are fluid and confident\\n\\n Her expressions vary from a seductive gaze at the camera to a playful smile. The video is well-lit and appears to be professionally shot, with a clear focus on the woman's dance and attire. \\n\\nsh4rpn3ss 4k HDR. clear skin, masterpiece, subscatering photorealistic skin texture, detailed skin, visible pores, subsurface scattering, fine vellus hair, subtle skin imperfections, natural freckles, subsurface scattering,soft natural volumetric cinematic light, 8k RAW photo, sharp focus, f/1.8 aperture, and shallow depth of field",
      "negative_prompt": "\u8272\u8c03\u8273\u4e3d\uff0c\u8fc7\u66dd\uff0c\u9759\u6001\uff0c\u7ec6\u8282\u6a21\u7cca\u4e0d\u6e05\uff0c\u5b57\u5e55\uff0c\u98ce\u683c\uff0c\u4f5c\u54c1\uff0c\u753b\u4f5c\uff0c\u753b\u9762\uff0c\u9759\u6b62\uff0c\u6574\u4f53\u53d1\u7070\uff0c\u6700\u5dee\u8d28\u91cf\uff0c\u4f4e\u8d28\u91cf\uff0cJPEG\u538b\u7f29\u6b8b\u7559\uff0c\u4e11\u964b\u7684\uff0c\u6b8b\u7f3a\u7684\uff0c\u591a\u4f59\u7684\u624b\u6307\uff0c\u753b\u5f97\u4e0d\u597d\u7684\u624b\u90e8\uff0c\u753b\u5f97\u4e0d\u597d\u7684\u8138\u90e8\uff0c\u7578\u5f62\u7684\uff0c\u6bc1\u5bb9\u7684\uff0c\u5f62\u6001\u7578\u5f62\u7684\u80a2\u4f53\uff0c\u624b\u6307\u878d\u5408\uff0c\u9759\u6b62\u4e0d\u52a8\u7684\u753b\u9762\uff0c\u6742\u4e71\u7684\u80cc\u666f\uff0c\u4e09\u6761\u817f\uff0c\u80cc\u666f\u4eba\u5f88\u591a\uff0c\u5012\u7740\u8d70, plastic skin, doll-like, airbrushed, perfectly smooth skin, cartoon, anime, 3d render, CGI, porcelain skin, oversaturated, unnatural color, jpeg artifacts, blurry, low quality, deformed, mutated",
      "latent_path": "output/prompt-runner/20250811_191908/latents/job_003.latent",
      "reference_image_path": "output/prompt-runner/20250811_191908/references/job_002_ref.png"
    },
    {
      "job_id": "bd2ce051-36e7-4095-a9a3-fa75ee93892a",
      "job_number": 5,
      "job_type": "HIGH",
      "frames_to_render": 101,
      "start_frame": 202,
      "video_name": "2025-05-02_19-39-31_UTC",
      "positive_prompt": "The setting to be an indoor space of a bedroom. OFA1M1 is wearing black short panties and a white crop bra\\nOFA1M1 is dancing to an upbeat, rhythmic song. Her movements are fluid and confident\\n\\n Her expressions vary from a seductive gaze at the camera to a playful smile. The video is well-lit and appears to be professionally shot, with a clear focus on the woman's dance and attire. \\n\\nsh4rpn3ss 4k HDR. clear skin, masterpiece, subscatering photorealistic skin texture, detailed skin, visible pores, subsurface scattering, fine vellus hair, subtle skin imperfections, natural freckles, subsurface scattering,soft natural volumetric cinematic light, 8k RAW photo, sharp focus, f/1.8 aperture, and shallow depth of field",
      "negative_prompt": "\u8272\u8c03\u8273\u4e3d\uff0c\u8fc7\u66dd\uff0c\u9759\u6001\uff0c\u7ec6\u8282\u6a21\u7cca\u4e0d\u6e05\uff0c\u5b57\u5e55\uff0c\u98ce\u683c\uff0c\u4f5c\u54c1\uff0c\u753b\u4f5c\uff0c\u753b\u9762\uff0c\u9759\u6b62\uff0c\u6574\u4f53\u53d1\u7070\uff0c\u6700\u5dee\u8d28\u91cf\uff0c\u4f4e\u8d28\u91cf\uff0cJPEG\u538b\u7f29\u6b8b\u7559\uff0c\u4e11\u964b\u7684\uff0c\u6b8b\u7f3a\u7684\uff0c\u591a\u4f59\u7684\u624b\u6307\uff0c\u753b\u5f97\u4e0d\u597d\u7684\u624b\u90e8\uff0c\u753b\u5f97\u4e0d\u597d\u7684\u8138\u90e8\uff0c\u7578\u5f62\u7684\uff0c\u6bc1\u5bb9\u7684\uff0c\u5f62\u6001\u7578\u5f62\u7684\u80a2\u4f53\uff0c\u624b\u6307\u878d\u5408\uff0c\u9759\u6b62\u4e0d\u52a8\u7684\u753b\u9762\uff0c\u6742\u4e71\u7684\u80cc\u666f\uff0c\u4e09\u6761\u817f\uff0c\u80cc\u666f\u4eba\u5f88\u591a\uff0c\u5012\u7740\u8d70, plastic skin, doll-like, airbrushed, perfectly smooth skin, cartoon, anime, 3d render, CGI, porcelain skin, oversaturated, unnatural color, jpeg artifacts, blurry, low quality, deformed, mutated",
      "latent_path": "output/prompt-runner/20250811_191908/latents/job_005.latent",
      "reference_image_path": "output/prompt-runner/20250811_191908/references/job_004_ref.png"
    },
    {
      "job_id": "abee61da-2584-485d-a3fb-00e31317071d",
      "job_number": 6,
      "job_type": "LOW",
      "frames_to_render": 101,
      "start_frame": 202,
      "video_name": "2025-05-02_19-39-31_UTC",
      "positive_prompt": "The setting to be an indoor space of a bedroom. OFA1M1 is wearing black short panties and a white crop bra\\nOFA1M1 is dancing to an upbeat, rhythmic song. Her movements are fluid and confident\\n\\n Her expressions vary from a seductive gaze at the camera to a playful smile. The video is well-lit and appears to be professionally shot, with a clear focus on the woman's dance and attire. \\n\\nsh4rpn3ss 4k HDR. clear skin, masterpiece, subscatering photorealistic skin texture, detailed skin, visible pores, subsurface scattering, fine vellus hair, subtle skin imperfections, natural freckles, subsurface scattering,soft natural volumetric cinematic light, 8k RAW photo, sharp focus, f/1.8 aperture, and shallow depth of field",
      "negative_prompt": "\u8272\u8c03\u8273\u4e3d\uff0c\u8fc7\u66dd\uff0c\u9759\u6001\uff0c\u7ec6\u8282\u6a21\u7cca\u4e0d\u6e05\uff0c\u5b57\u5e55\uff0c\u98ce\u683c\uff0c\u4f5c\u54c1\uff0c\u753b\u4f5c\uff0c\u753b\u9762\uff0c\u9759\u6b62\uff0c\u6574\u4f53\u53d1\u7070\uff0c\u6700\u5dee\u8d28\u91cf\uff0c\u4f4e\u8d28\u91cf\uff0cJPEG\u538b\u7f29\u6b8b\u7559\uff0c\u4e11\u964b\u7684\uff0c\u6b8b\u7f3a\u7684\uff0c\u591a\u4f59\u7684\u624b\u6307\uff0c\u753b\u5f97\u4e0d\u597d\u7684\u624b\u90e8\uff0c\u753b\u5f97\u4e0d\u597d\u7684\u8138\u90e8\uff0c\u7578\u5f62\u7684\uff0c\u6bc1\u5bb9\u7684\uff0c\u5f62\u6001\u7578\u5f62\u7684\u80a2\u4f53\uff0c\u624b\u6307\u878d\u5408\uff0c\u9759\u6b62\u4e0d\u52a8\u7684\u753b\u9762\uff0c\u6742\u4e71\u7684\u80cc\u666f\uff0c\u4e09\u6761\u817f\uff0c\u80cc\u666f\u4eba\u5f88\u591a\uff0c\u5012\u7740\u8d70, plastic skin, doll-like, airbrushed, perfectly smooth skin, cartoon, anime, 3d render, CGI, porcelain skin, oversaturated, unnatural color, jpeg artifacts, blurry, low quality, deformed, mutated",
      "latent_path": "output/prompt-runner/20250811_191908/latents/job_005.latent",
      "reference_image_path": "output/prompt-runner/20250811_191908/references/job_004_ref.png"
    },
    {
      "job_id": "2abfd50e-9623-4430-9f60-af73ca766796",
      "job_number": 7,
      "job_type": "HIGH",
      "frames_to_render": 101,
      "start_frame": 303,
      "video_name": "2025-05-02_19-39-31_UTC",
      "positive_prompt": "The setting to be an indoor space of a bedroom. OFA1M1 is wearing black short panties and a white crop bra\\nOFA1M1 is dancing to an upbeat, rhythmic song. Her movements are fluid and confident\\n\\n Her expressions vary from a seductive gaze at the camera to a playful smile. The video is well-lit and appears to be professionally shot, with a clear focus on the woman's dance and attire. \\n\\nsh4rpn3ss 4k HDR. clear skin, masterpiece, subscatering photorealistic skin texture, detailed skin, visible pores, subsurface scattering, fine vellus hair, subtle skin imperfections, natural freckles, subsurface scattering,soft natural volumetric cinematic light, 8k RAW photo, sharp focus, f/1.8 aperture, and shallow depth of field",
      "negative_prompt": "\u8272\u8c03\u8273\u4e3d\uff0c\u8fc7\u66dd\uff0c\u9759\u6001\uff0c\u7ec6\u8282\u6a21\u7cca\u4e0d\u6e05\uff0c\u5b57\u5e55\uff0c\u98ce\u683c\uff0c\u4f5c\u54c1\uff0c\u753b\u4f5c\uff0c\u753b\u9762\uff0c\u9759\u6b62\uff0c\u6574\u4f53\u53d1\u7070\uff0c\u6700\u5dee\u8d28\u91cf\uff0c\u4f4e\u8d28\u91cf\uff0cJPEG\u538b\u7f29\u6b8b\u7559\uff0c\u4e11\u964b\u7684\uff0c\u6b8b\u7f3a\u7684\uff0c\u591a\u4f59\u7684\u624b\u6307\uff0c\u753b\u5f97\u4e0d\u597d\u7684\u624b\u90e8\uff0c\u753b\u5f97\u4e0d\u597d\u7684\u8138\u90e8\uff0c\u7578\u5f62\u7684\uff0c\u6bc1\u5bb9\u7684\uff0c\u5f62\u6001\u7578\u5f62\u7684\u80a2\u4f53\uff0c\u624b\u6307\u878d\u5408\uff0c\u9759\u6b62\u4e0d\u52a8\u7684\u753b\u9762\uff0c\u6742\u4e71\u7684\u80cc\u666f\uff0c\u4e09\u6761\u817f\uff0c\u80cc\u666f\u4eba\u5f88\u591a\uff0c\u5012\u7740\u8d70, plastic skin, doll-like, airbrushed, perfectly smooth skin, cartoon, anime, 3d render, CGI, porcelain skin, oversaturated, unnatural color, jpeg artifacts, blurry, low quality, deformed, mutated",
      "latent_path": "output/prompt-runner/20250811_191908/latents/job_007.latent",
      "reference_image_path": "output/prompt-runner/20250811_191908/references/job_006_ref.png"
    },
    {
      "job_id": "2799cdb3-5a7f-4033-9ee5-5257749473e8",
      "job_number": 8,
      "job_type": "LOW",
      "frames_to_render": 101,
      "start_frame": 303,
      "video_name": "2025-05-02_19-39-31_UTC",
      "positive_prompt": "The setting to be an indoor space of a bedroom. OFA1M1 is wearing black short panties and a white crop bra\\nOFA1M1 is dancing to an upbeat, rhythmic song. Her movements are fluid and confident\\n\\n Her expressions vary from a seductive gaze at the camera to a playful smile. The video is well-lit and appears to be professionally shot, with a clear focus on the woman's dance and attire. \\n\\nsh4rpn3ss 4k HDR. clear skin, masterpiece, subscatering photorealistic skin texture, detailed skin, visible pores, subsurface scattering, fine vellus hair, subtle skin imperfections, natural freckles, subsurface scattering,soft natural volumetric cinematic light, 8k RAW photo, sharp focus, f/1.8 aperture, and shallow depth of field",
      "negative_prompt": "\u8272\u8c03\u8273\u4e3d\uff0c\u8fc7\u66dd\uff0c\u9759\u6001\uff0c\u7ec6\u8282\u6a21\u7cca\u4e0d\u6e05\uff0c\u5b57\u5e55\uff0c\u98ce\u683c\uff0c\u4f5c\u54c1\uff0c\u753b\u4f5c\uff0c\u753b\u9762\uff0c\u9759\u6b62\uff0c\u6574\u4f53\u53d1\u7070\uff0c\u6700\u5dee\u8d28\u91cf\uff0c\u4f4e\u8d28\u91cf\uff0cJPEG\u538b\u7f29\u6b8b\u7559\uff0c\u4e11\u964b\u7684\uff0c\u6b8b\u7f3a\u7684\uff0c\u591a\u4f59\u7684\u624b\u6307\uff0c\u753b\u5f97\u4e0d\u597d\u7684\u624b\u90e8\uff0c\u753b\u5f97\u4e0d\u597d\u7684\u8138\u90e8\uff0c\u7578\u5f62\u7684\uff0c\u6bc1\u5bb9\u7684\uff0c\u5f62\u6001\u7578\u5f62\u7684\u80a2\u4f53\uff0c\u624b\u6307\u878d\u5408\uff0c\u9759\u6b62\u4e0d\u52a8\u7684\u753b\u9762\uff0c\u6742\u4e71\u7684\u80cc\u666f\uff0c\u4e09\u6761\u817f\uff0c\u80cc\u666f\u4eba\u5f88\u591a\uff0c\u5012\u7740\u8d70, plastic skin, doll-like, airbrushed, perfectly smooth skin, cartoon, anime, 3d render, CGI, porcelain skin, oversaturated, unnatural color, jpeg artifacts, blurry, low quality, deformed, mutated",
      "latent_path": "output/prompt-runner/20250811_191908/latents/job_007.latent",
      "reference_image_path": "output/prompt-runner/20250811_191908/references/job_006_ref.png"
    },
    {
      "job_id": "ad9a390d-9b98-4be8-aa2e-4315eaec5426",
      "job_number": 9,
      "job_type": "HIGH",
      "frames_to_render": 96,
      "start_frame": 404,
      "video_name": "2025-05-02_19-39-31_UTC",
      "positive_prompt": "The setting to be an indoor space of a bedroom. OFA1M1 is wearing black short panties and a white crop bra\\nOFA1M1 is dancing to an upbeat, rhythmic song. Her movements are fluid and confident\\n\\n Her expressions vary from a seductive gaze at the camera to a playful smile. The video is well-lit and appears to be professionally shot, with a clear focus on the woman's dance and attire. \\n\\nsh4rpn3ss 4k HDR. clear skin, masterpiece, subscatering photorealistic skin texture, detailed skin, visible pores, subsurface scattering, fine vellus hair, subtle skin imperfections, natural freckles, subsurface scattering,soft natural volumetric cinematic light, 8k RAW photo, sharp focus, f/1.8 aperture, and shallow depth of field",
      "negative_prompt": "\u8272\u8c03\u8273\u4e3d\uff0c\u8fc7\u66dd\uff0c\u9759\u6001\uff0c\u7ec6\u8282\u6a21\u7cca\u4e0d\u6e05\uff0c\u5b57\u5e55\uff0c\u98ce\u683c\uff0c\u4f5c\u54c1\uff0c\u753b\u4f5c\uff0c\u753b\u9762\uff0c\u9759\u6b62\uff0c\u6574\u4f53\u53d1\u7070\uff0c\u6700\u5dee\u8d28\u91cf\uff0c\u4f4e\u8d28\u91cf\uff0cJPEG\u538b\u7f29\u6b8b\u7559\uff0c\u4e11\u964b\u7684\uff0c\u6b8b\u7f3a\u7684\uff0c\u591a\u4f59\u7684\u624b\u6307\uff0c\u753b\u5f97\u4e0d\u597d\u7684\u624b\u90e8\uff0c\u753b\u5f97\u4e0d\u597d\u7684\u8138\u90e8\uff0c\u7578\u5f62\u7684\uff0c\u6bc1\u5bb9\u7684\uff0c\u5f62\u6001\u7578\u5f62\u7684\u80a2\u4f53\uff0c\u624b\u6307\u878d\u5408\uff0c\u9759\u6b62\u4e0d\u52a8\u7684\u753b\u9762\uff0c\u6742\u4e71\u7684\u80cc\u666f\uff0c\u4e09\u6761\u817f\uff0c\u80cc\u666f\u4eba\u5f88\u591a\uff0c\u5012\u7740\u8d70, plastic skin, doll-like, airbrushed, perfectly smooth skin, cartoon, anime, 3d render, CGI, porcelain skin, oversaturated, unnatural color, jpeg artifacts, blurry, low quality, deformed, mutated",
      "latent_path": "output/prompt-runner/20250811_191908/latents/job_009.latent",
      "reference_image_path": "output/prompt-runner/20250811_191908/references/job_008_ref.png"
    },
    {
      "job_id": "05c7e250-65de-4257-baa0-7b38301f080d",
      "job_number": 10,
      "job_type": "LOW",
      "frames_to_render": 96,
      "start_frame": 404,
      "video_name": "2025-05-02_19-39-31_UTC",
      "positive_prompt": "The setting to be an indoor space of a bedroom. OFA1M1 is wearing black short panties and a white crop bra\\nOFA1M1 is dancing to an upbeat, rhythmic song. Her movements are fluid and confident\\n\\n Her expressions vary from a seductive gaze at the camera to a playful smile. The video is well-lit and appears to be professionally shot, with a clear focus on the woman's dance and attire. \\n\\nsh4rpn3ss 4k HDR. clear skin, masterpiece, subscatering photorealistic skin texture, detailed skin, visible pores, subsurface scattering, fine vellus hair, subtle skin imperfections, natural freckles, subsurface scattering,soft natural volumetric cinematic light, 8k RAW photo, sharp focus, f/1.8 aperture, and shallow depth of field",
      "negative_prompt": "\u8272\u8c03\u8273\u4e3d\uff0c\u8fc7\u66dd\uff0c\u9759\u6001\uff0c\u7ec6\u8282\u6a21\u7cca\u4e0d\u6e05\uff0c\u5b57\u5e55\uff0c\u98ce\u683c\uff0c\u4f5c\u54c1\uff0c\u753b\u4f5c\uff0c\u753b\u9762\uff0c\u9759\u6b62\uff0c\u6574\u4f53\u53d1\u7070\uff0c\u6700\u5dee\u8d28\u91cf\uff0c\u4f4e\u8d28\u91cf\uff0cJPEG\u538b\u7f29\u6b8b\u7559\uff0c\u4e11\u964b\u7684\uff0c\u6b8b\u7f3a\u7684\uff0c\u591a\u4f59\u7684\u624b\u6307\uff0c\u753b\u5f97\u4e0d\u597d\u7684\u624b\u90e8\uff0c\u753b\u5f97\u4e0d\u597d\u7684\u8138\u90e8\uff0c\u7578\u5f62\u7684\uff0c\u6bc1\u5bb9\u7684\uff0c\u5f62\u6001\u7578\u5f62\u7684\u80a2\u4f53\uff0c\u624b\u6307\u878d\u5408\uff0c\u9759\u6b62\u4e0d\u52a8\u7684\u753b\u9762\uff0c\u6742\u4e71\u7684\u80cc\u666f\uff0c\u4e09\u6761\u817f\uff0c\u80cc\u666f\u4eba\u5f88\u591a\uff0c\u5012\u7740\u8d70, plastic skin, doll-like, airbrushed, perfectly smooth skin, cartoon, anime, 3d render, CGI, porcelain skin, oversaturated, unnatural color, jpeg artifacts, blurry, low quality, deformed, mutated",
      "latent_path": "output/prompt-runner/20250811_191908/latents/job_009.latent",
      "reference_image_path": "output/prompt-runner/20250811_191908/references/job_008_ref.png"
    }
  ]
}